nsfwpy/__init__.py
nsfwpy/api.py
nsfwpy/cli.py
nsfwpy/nsfw.py
nsfwpy/nsfw_tflite.py
nsfwpy/server.py
nsfwpy-0.1.4.3.dist-info/LICENSE
nsfwpy-0.1.4.3.dist-info/METADATA
nsfwpy-0.1.4.3.dist-info/WHEEL
nsfwpy-0.1.4.3.dist-info/entry_points.txt
nsfwpy-0.1.4.3.dist-info/top_level.txt
nsfwpy-0.1.4.3.dist-info/RECORD
