Metadata-Version: 2.1
Name: nsfwpy
Version: 0.1.4.3
Summary: 基于OpenNSFW的图像内容检测工具
Home-page: https://github.com/HG-ha/nsfwpy
Author: YiMing
Author-email: 1790233968@qq.com
Classifier: Programming Language :: Python
Classifier: Programming Language :: Python :: 3 :: Only
Classifier: Operating System :: Microsoft :: Windows
Classifier: Operating System :: POSIX :: Linux
Classifier: Operating System :: MacOS
License-File: LICENSE
Requires-Dist: onnxruntime<=1.21.0
Requires-Dist: pillow<=11.1.0
Requires-Dist: fastapi<=0.115.11
Requires-Dist: uvicorn<=0.34.0
Requires-Dist: python-multipart<=0.0.20
Requires-Dist: numpy<=1.26.4
Requires-Dist: opencv-python-headless<=4.11.0.86
